NodeStats.py
shdw_node_stats-0.4.1.dist-info/LICENSE
shdw_node_stats-0.4.1.dist-info/METADATA
shdw_node_stats-0.4.1.dist-info/WHEEL
shdw_node_stats-0.4.1.dist-info/entry_points.txt
shdw_node_stats-0.4.1.dist-info/top_level.txt
shdw_node_stats-0.4.1.dist-info/RECORD
