Metadata-Version: 2.1
Name: shdw-node-stats
Version: 0.4.1
Summary: A tool to fetch and record ShadowDrive node statistics from an API and save them to a CSV file.
Author-email: AnyNodes <anynodes@outlook.com>
License: MIT
Project-URL: homepage, https://github.com/AnyNodes/shdw-node-stats#readme
Project-URL: issues, https://github.com/AnyNodes/shdw-node-stats/issues
Project-URL: repository, https://github.com/AnyNodes/shdw-node-stats.git
Project-URL: source, https://github.com/AnyNodes/shdw-node-stats.git
Keywords: API,ShadowDrive,statistics,CSV,shdw,solana,storage
Classifier: Programming Language :: Python :: 3
Classifier: License :: OSI Approved :: MIT License
Classifier: Operating System :: OS Independent
License-File: LICENSE
Requires-Dist: requests >=2.25.1
Requires-Dist: pandas >=1.2.3
Requires-Dist: tensorflow >=2.4.1
